mdup.py
mdup-0.3.0.dist-info/licenses/LICENSE
mdup-0.3.0.dist-info/METADATA
mdup-0.3.0.dist-info/WHEEL
mdup-0.3.0.dist-info/entry_points.txt
mdup-0.3.0.dist-info/top_level.txt
mdup-0.3.0.dist-info/RECORD
