Metadata-Version: 2.4
Name: mdup
Version: 0.3.0
Summary: Keep markdown files up-to-date.
Author: Alexandru Dinu
Requires-Python: >=3.8
License-File: LICENSE
Dynamic: license-file
